MusicSeparationYTMain/MusicSeparationYT.py
MusicSeparationYTMain/__init__.py
MusicSeparationYT-1.0.9.dist-info/LICENSE
MusicSeparationYT-1.0.9.dist-info/METADATA
MusicSeparationYT-1.0.9.dist-info/WHEEL
MusicSeparationYT-1.0.9.dist-info/top_level.txt
MusicSeparationYT-1.0.9.dist-info/RECORD
