Metadata-Version: 2.1
Name: MusicSeparationYT
Version: 1.0.9
Summary: this tool music download and seprate
Author: Y-Ryohei
License: MIT
License-File: LICENSE
